simnet/__init__.py
simnet/client/__init__.py
simnet/client/base.py
simnet/client/components/__init__.py
simnet/client/components/auth.py
simnet/client/components/calculator/__init__.py
simnet/client/components/calculator/genshin.py
simnet/client/components/calculator/starrail.py
simnet/client/components/chronicle/__init__.py
simnet/client/components/chronicle/base.py
simnet/client/components/chronicle/genshin.py
simnet/client/components/chronicle/starrail.py
simnet/client/components/chronicle/zzz.py
simnet/client/components/daily.py
simnet/client/components/diary/__init__.py
simnet/client/components/diary/base.py
simnet/client/components/diary/genshin.py
simnet/client/components/diary/starrail.py
simnet/client/components/diary/zzz.py
simnet/client/components/lab.py
simnet/client/components/self_help/__init__.py
simnet/client/components/self_help/base.py
simnet/client/components/self_help/starrail.py
simnet/client/components/self_help/zzz.py
simnet/client/components/transaction.py
simnet/client/components/verify.py
simnet/client/components/wish/__init__.py
simnet/client/components/wish/base.py
simnet/client/components/wish/genshin.py
simnet/client/components/wish/starrail.py
simnet/client/components/wish/zzz.py
simnet/client/cookies.py
simnet/client/genshin.py
simnet/client/genshin.pyi
simnet/client/headers.py
simnet/client/routes.py
simnet/client/starrail.py
simnet/client/starrail.pyi
simnet/client/zzz.py
simnet/errors.py
simnet/models/__init__.py
simnet/models/base.py
simnet/models/diary.py
simnet/models/genshin/__init__.py
simnet/models/genshin/calculator.py
simnet/models/genshin/character.py
simnet/models/genshin/chronicle/__init__.py
simnet/models/genshin/chronicle/abyss.py
simnet/models/genshin/chronicle/achievement.py
simnet/models/genshin/chronicle/act_calendar.py
simnet/models/genshin/chronicle/character_detail.py
simnet/models/genshin/chronicle/characters.py
simnet/models/genshin/chronicle/img_theater.py
simnet/models/genshin/chronicle/notes.py
simnet-0.2.0.dist-info/LICENSE
simnet-0.2.0.dist-info/METADATA
simnet-0.2.0.dist-info/WHEEL
simnet-0.2.0.dist-info/RECORD
