Metadata-Version: 2.1
Name: SIMNet
Version: 0.2.0
Summary: Modern API wrapper for Genshin Impact & Honkai: Star Rail built on asyncio and pydantic.
License: MIT
Author: PaiGramTeam
Requires-Python: >=3.9,<4.0
Classifier: License :: OSI Approved :: MIT License
Classifier: Programming Language :: Python :: 3
Classifier: Programming Language :: Python :: 3.9
Classifier: Programming Language :: Python :: 3.10
Classifier: Programming Language :: Python :: 3.11
Classifier: Programming Language :: Python :: 3.12
Classifier: Programming Language :: Python :: 3.13
Requires-Dist: httpx (>=0.25.0)
Requires-Dist: pydantic (>=2.0.0,<3.0.0)
